nameko_zipkin/__init__.py
nameko_zipkin/constants.py
nameko_zipkin/method_proxy.py
nameko_zipkin/provider.py
nameko_zipkin/transport.py
nameko_zipkin/utils.py
nameko_zipkin-0.1.2.dist-info/DESCRIPTION.rst
nameko_zipkin-0.1.2.dist-info/METADATA
nameko_zipkin-0.1.2.dist-info/RECORD
nameko_zipkin-0.1.2.dist-info/WHEEL
nameko_zipkin-0.1.2.dist-info/metadata.json
nameko_zipkin-0.1.2.dist-info/top_level.txt
